decider_bwa_se/__init__.py
decider_bwa_se/__main__.py
decider_bwa_se/main.py
decider_bwa_se-0.4.dist-info/DESCRIPTION.rst
decider_bwa_se-0.4.dist-info/METADATA
decider_bwa_se-0.4.dist-info/RECORD
decider_bwa_se-0.4.dist-info/WHEEL
decider_bwa_se-0.4.dist-info/metadata.json
decider_bwa_se-0.4.dist-info/top_level.txt
decider_se_pe/__init__.py
decider_se_pe/__main__.py
decider_se_pe/main.py
