Metadata-Version: 2.0
Name: decider-bwa-se
Version: 0.4
Summary: match readgroup and fastq outputs
Home-page: https://github.com/jeremiahsavage/decider_bwa_se
Author: Jeremiah H. Savage
Author-email: jeremiahsavage@gmail.com
License: Apache 2.0
Platform: UNKNOWN
Classifier: Development Status :: 3 - Alpha
Classifier: Intended Audience :: Developers
Classifier: License :: OSI Approved :: Apache Software License
Classifier: Programming Language :: Python
Classifier: Programming Language :: Python :: 2
Classifier: Programming Language :: Python :: 3
Requires-Dist: biopython
Requires-Dist: cdis-pipe-utils
Requires-Dist: cython
Requires-Dist: pandas
Requires-Dist: sqlalchemy
